README.md
setup.cfg
setup.py
eis/__init__.py
eis/payment/__init__.py
eis/payment/api_client.py
eis/payment/configuration.py
eis/payment/exceptions.py
eis/payment/model_utils.py
eis/payment/rest.py
eis/payment/api/__init__.py
eis/payment/api/bank_accounts_api.py
eis/payment/api/bank_orders_api.py
eis/payment/api/bank_transaction_api.py
eis/payment/api/credit_allocation_api.py
eis/payment/api/exceeding_credits_api.py
eis/payment/api/health_check_api.py
eis/payment/api/payment_methods_api.py
eis/payment/api/payment_reminders_api.py
eis/payment/api/payment_setup_api.py
eis/payment/api/payments_api.py
eis/payment/api/policy_payment_methods_api.py
eis/payment/api/refunds_api.py
eis/payment/api/tenant_bank_account_api.py
eis/payment/api/webhooks_api.py
eis/payment/apis/__init__.py
eis/payment/model/__init__.py
eis/payment/model/activate_policy_payment_method_request_dto.py
eis/payment/model/bank_account_class.py
eis/payment/model/bank_account_class_without_expand_properties.py
eis/payment/model/bank_order_class.py
eis/payment/model/bank_order_entity.py
eis/payment/model/bank_order_xml_file_class.py
eis/payment/model/bank_order_xml_file_entity.py
eis/payment/model/bank_transaction_class.py
eis/payment/model/bank_transaction_class_without_expand_properties.py
eis/payment/model/bank_transaction_entity.py
eis/payment/model/bank_transaction_invoice_class.py
eis/payment/model/bank_transaction_invoice_entity.py
eis/payment/model/bank_transfer_dto.py
eis/payment/model/billing_address_dto.py
eis/payment/model/billing_profile_dto.py
eis/payment/model/billing_profile_limited_response_dto.py
eis/payment/model/card_details_dto.py
eis/payment/model/complete_adyen_payment_setup_request_dto.py
eis/payment/model/complete_braintree_payment_setup_request_dto.py
eis/payment/model/complete_eis_payment_setup_request_dto.py
eis/payment/model/complete_payment_setup_request_dto.py
eis/payment/model/complete_payment_setup_response_class.py
eis_payments.egg-info/PKG-INFO
eis_payments.egg-info/SOURCES.txt
eis_payments.egg-info/dependency_links.txt
eis_payments.egg-info/requires.txt
eis_payments.egg-info/top_level.txt
