Metadata-Version: 2.1
Name: eis-payments
Version: 1.10.0
Summary: Emil Payment Service
Home-page: UNKNOWN
Author: Contact us
Author-email: kontakt@emil.de
License: UNKNOWN
Keywords: OpenAPI,OpenAPI-Generator,Emil Payment Service
Platform: UNKNOWN
Requires-Python: >=3.6
